secretbox/__init__.py
secretbox/aws_loader.py
secretbox/awsparameterstore_loader.py
secretbox/awssecret_loader.py
secretbox/envfile_loader.py
secretbox/environ_loader.py
secretbox/exceptions.py
secretbox/loader.py
secretbox/py.typed
secretbox/secretbox.py
secretbox-2.8.0.dist-info/LICENSE
secretbox-2.8.0.dist-info/METADATA
secretbox-2.8.0.dist-info/WHEEL
secretbox-2.8.0.dist-info/top_level.txt
secretbox-2.8.0.dist-info/RECORD
