Metadata-Version: 2.1
Name: secretbox
Version: 2.8.0
Summary: A library that offers a simple method of loading and accessing environmental variables and `.env` file values.
Author-email: Preocts <preocts@preocts.com>
License: MIT License
Project-URL: homepage, https://github.com/Preocts/secretbox
Classifier: License :: OSI Approved :: MIT License
Classifier: Programming Language :: Python :: 3
Classifier: Programming Language :: Python :: 3 :: Only
Classifier: Programming Language :: Python :: Implementation :: CPython
Requires-Python: >=3.8
License-File: LICENSE
Provides-Extra: aws
Requires-Dist: boto3 (>=1.18.56) ; extra == 'aws'
Requires-Dist: boto3-stubs[secretsmanager] (>=1.18.55) ; extra == 'aws'
Requires-Dist: boto3-stubs[ssm] (>=1.18.55) ; extra == 'aws'
Provides-Extra: dev
Requires-Dist: pre-commit ; extra == 'dev'
Requires-Dist: black ; extra == 'dev'
Requires-Dist: mypy ; extra == 'dev'
Requires-Dist: flake8 ; extra == 'dev'
Requires-Dist: flake8-builtins ; extra == 'dev'
Requires-Dist: flake8-pep585 ; extra == 'dev'
Provides-Extra: test
Requires-Dist: pytest ; extra == 'test'
Requires-Dist: pytest-randomly ; extra == 'test'
Requires-Dist: coverage ; extra == 'test'
Requires-Dist: tox ; extra == 'test'
